LICENSE
README.md
setup.py
src/odesf.py
src/process.py
src/odesf.egg-info/PKG-INFO
src/odesf.egg-info/SOURCES.txt
src/odesf.egg-info/dependency_links.txt
src/odesf.egg-info/top_level.txt