Metadata-Version: 2.1
Name: odesf
Version: 0.0.4
Summary: Ordinary Differential Equations String Function generator.
Author: Xiaodu Hu
Author-email: xiaodu.hu@outlook.com
License: MIT
Keywords: python,ode,string,function
Classifier: Development Status :: 1 - Planning
Classifier: Intended Audience :: Developers
Classifier: Programming Language :: Python :: 3
Classifier: Operating System :: Unix
Classifier: Operating System :: MacOS
License-File: LICENSE
